{
	"instance" : {
		"asString" : "JesusMariAguirre 9/21/2017 19:58",
		"value" : " 9/16/2017 22:22:25",
		"at:" : " 9/16/2017 22:22:25",
		"doesNotUnderstand:" : " 9/16/2017 22:22:25",
		"valuesIn:" : " 9/16/2017 22:22:25",
		"name" : " 9/16/2017 22:22:25"
	},
	"class" : {
		"newFrom:" : "JesusMari 10/13/2017 21:37",
		"fromAssociations:" : "JesusMari 10/20/2017 22:03",
		"pool" : "Jesús 10/20/2017 18:57:14",
		"fromDictionary:" : "Jesús 10/20/2017 18:57:14",
		"fromCollection:" : "Jesús 10/20/2017 18:57:14"
	}
}